{"Protocol":6,"SrcAddress":"172.17.144.61","SrcPort":49733,"DstAddress":"20.114.58.89","DstPort":443,"BytesOut":2028,"PacketsOut":14,"BytesIn":4177,"PacketsIn":11,"Start":1722307201.869506,"Duration":0.8912370204925537,"TlsClientVersion":5,"TlsServerVersion":null,"ServerName":["msedge.api.cdp.microsoft.com"],"TlsClientCipherSuites":["c02c","c02b","c030","c02f","c024","c023","c028","c027","c00a","c009","c014","c013","009d","009c","003d","003c","0035","002f","000a"],"TlsClientExtensions":[{"server_name":"001f00001c6d73656467652e6170692e6364702e6d6963726f736f66742e636f6d"},{"status_request":"0100000000"},{"supported_groups":"0006001d00170018"},{"ec_point_formats":"0100"},{"signature_algorithms":"0018080408050806040105010201040305030203020206010603"},{"session_ticket":""},{"application_layer_protocol_negotiation":"000c02683208687474702f312e31"},{"extended_master_secret":""},{"renegotiation_info":"00"}],"TlsServerCipherSuite":null,"TlsServerExtensions":null,"RecordSequence":[208,102,1,40,82,416,831,33,230,35],"ProcessName":null,"ProcessId":null,"Label":null,"Sample":"MirosoftEdge_20240730"}
{"Protocol":6,"SrcAddress":"172.17.144.61","SrcPort":49755,"DstAddress":"20.189.173.21","DstPort":443,"BytesOut":6819,"PacketsOut":10,"BytesIn":2154,"PacketsIn":8,"Start":1722307211.099031,"Duration":1.1080989837646484,"TlsClientVersion":5,"TlsServerVersion":null,"ServerName":["watson.events.data.microsoft.com"],"TlsClientCipherSuites":["c02c","c02b","c030","c02f","c024","c023","c028","c027","c00a","c009","c014","c013","009d","009c","003d","003c","0035","002f","000a"],"TlsClientExtensions":[{"server_name":"0023000020776174736f6e2e6576656e74732e646174612e6d6963726f736f66742e636f6d"},{"status_request":"0100000000"},{"supported_groups":"0006001d00170018"},{"ec_point_formats":"0100"},{"signature_algorithms":"0018080408050806040105010201040305030203020206010603"},{"session_ticket":""},{"application_layer_protocol_negotiation":"000c02683208687474702f312e31"},{"extended_master_secret":""},{"renegotiation_info":"00"}],"TlsServerCipherSuite":null,"TlsServerExtensions":null,"RecordSequence":[212,102,1,40,1117,4120,1192],"ProcessName":null,"ProcessId":null,"Label":null,"Sample":"MirosoftEdge_20240730"}
{"Protocol":6,"SrcAddress":"172.17.144.61","SrcPort":49765,"DstAddress":"20.189.173.21","DstPort":443,"BytesOut":6739,"PacketsOut":8,"BytesIn":2165,"PacketsIn":6,"Start":1722307221.379914,"Duration":0.6880788803100586,"TlsClientVersion":5,"TlsServerVersion":null,"ServerName":["watson.events.data.microsoft.com"],"TlsClientCipherSuites":["c02c","c02b","c030","c02f","c024","c023","c028","c027","c00a","c009","c014","c013","009d","009c","003d","003c","0035","002f","000a"],"TlsClientExtensions":[{"server_name":"0023000020776174736f6e2e6576656e74732e646174612e6d6963726f736f66742e636f6d"},{"status_request":"0100000000"},{"supported_groups":"0006001d00170018"},{"ec_point_formats":"0100"},{"signature_algorithms":"0018080408050806040105010201040305030203020206010603"},{"session_ticket":""},{"application_layer_protocol_negotiation":"000c02683208687474702f312e31"},{"extended_master_secret":""},{"renegotiation_info":"00"}],"TlsServerCipherSuite":null,"TlsServerExtensions":null,"RecordSequence":[212,102,1,40,1117,4120,1112],"ProcessName":null,"ProcessId":null,"Label":null,"Sample":"MirosoftEdge_20240730"}
